LICENSE
README.md
setup.cfg
setup.py
insuranceqa_data/LICENSE
insuranceqa_data/__init__.py
insuranceqa_data.egg-info/PKG-INFO
insuranceqa_data.egg-info/SOURCES.txt
insuranceqa_data.egg-info/dependency_links.txt
insuranceqa_data.egg-info/requires.txt
insuranceqa_data.egg-info/top_level.txt