Metadata-Version: 2.1
Name: insuranceqa-data
Version: 2.5.5
Summary: Insuranceqa Corpus in Chinese for Machine Learning
Home-page: https://github.com/chatopera/insuranceqa-corpus-zh
Author: Hai Liang Wang
Author-email: hailiang.hl.wang@gmail.com
License: Chunsong Public License, version 1.0
Keywords: corpus,machine-learning,deep-learning,NLP,question-answering
Classifier: Intended Audience :: Developers
Classifier: Operating System :: OS Independent
Classifier: Natural Language :: Chinese (Simplified)
Classifier: Natural Language :: Chinese (Traditional)
Classifier: Programming Language :: Python
Classifier: Programming Language :: Python :: 2
Classifier: Programming Language :: Python :: 2.7
Classifier: Programming Language :: Python :: 3
Classifier: Programming Language :: Python :: 3.4
Classifier: Programming Language :: Python :: 3.5
Classifier: Programming Language :: Python :: 3.6
Classifier: Topic :: Text Processing
Classifier: Topic :: Text Processing :: Indexing
Classifier: Topic :: Text Processing :: Linguistic
License-File: LICENSE
